quatex/__init__.py
quatex/market/__init__.py
quatex/market/assetinfo.py
quatex/market/data/listing_status.csv
quatex/market/data/listing_status.csv.meta
quatex/market/marketcalender.py
quatex/market/marketdata.py
quatex/market/providers/marketdataapp.py
quatex/utility/__init__.py
quatex/utility/config.py
quatex-1.0.2.dist-info/METADATA
quatex-1.0.2.dist-info/WHEEL
quatex-1.0.2.dist-info/RECORD
